django_media_explorer-0.3.10.dist-info/metadata.json
django_media_explorer-0.3.10.dist-info/METADATA
django_media_explorer-0.3.10.dist-info/WHEEL
django_media_explorer-0.3.10.dist-info/RECORD
django_media_explorer-0.3.10.dist-info/top_level.txt
django_media_explorer-0.3.10.dist-info/DESCRIPTION.rst
media_explorer/settings.py
media_explorer/admin.py
media_explorer/widgets.py
media_explorer/views.py
media_explorer/models.py
media_explorer/forms.py
media_explorer/helpers.py
media_explorer/urls.py
media_explorer/django_rest_framework.py
media_explorer/__init__.py
media_explorer/fields.py
media_explorer/migrations/__init__.py
media_explorer/tests/__init__.py
media_explorer/tests/elements/Oxfam-Cambodia.jpg
media_explorer/tests/elements/tests.py
media_explorer/tests/elements/__init__.py
media_explorer/tests/galleries/tests.py
media_explorer/tests/galleries/__init__.py
media_explorer/tests/customfields/models.py
media_explorer/tests/customfields/tests.py
media_explorer/tests/customfields/__init__.py
media_explorer/tests/customfields/migrations/__init__.py
media_explorer/templates/media_explorer/inline_image.html
media_explorer/templates/media_explorer/video.html
media_explorer/templates/media_explorer/gallery_slick.html
media_explorer/templates/media_explorer/gallery_galleria.html
media_explorer/templates/admin/media_field.html
media_explorer/templates/admin/media_explorer/base.html
media_explorer/static/fonts/glyphicons-halflings-regular.svg
media_explorer/static/fonts/glyphicons-halflings-regular.woff2
media_explorer/static/fonts/glyphicons-halflings-regular.woff
media_explorer/static/fonts/glyphicons-halflings-regular.eot
media_explorer/static/fonts/glyphicons-halflings-regular.ttf
media_explorer/static/slick/fonts/slick.ttf
media_explorer/static/slick/fonts/slick.svg
media_explorer/static/slick/fonts/slick.eot
media_explorer/static/slick/fonts/slick.woff
media_explorer/static/slick/js/slick.min.js
media_explorer/static/slick/js/slick.js
media_explorer/static/slick/js/oa.slick.js
media_explorer/static/slick/img/prev_gray.png
media_explorer/static/slick/img/ajax-loader.gif
media_explorer/static/slick/img/next_gray.png
media_explorer/static/slick/img/next.png
media_explorer/static/slick/img/prev.png
