Metadata-Version: 2.0
Name: django-media-explorer
Version: 0.3.10
Summary: A Django application to manage your images, video links, embeds and slideshows.
Home-page: https://github.com/oxfamamerica/django-media-explorer
Author: Oxfam America Web Team
Author-email: webmaster@oxfamamerica.org
License: MIT
Download-URL: https://pypi.python.org/pypi/django-media-explorer/
Keywords: multimedia,media,video,gallery
Platform: UNKNOWN
Classifier: Development Status :: 3 - Alpha
Classifier: Environment :: Web Environment
Classifier: Framework :: Django
Classifier: License :: OSI Approved :: MIT License
Classifier: Intended Audience :: Developers
Classifier: Operating System :: OS Independent
Classifier: Programming Language :: Python
Classifier: Topic :: Multimedia :: Video
Classifier: Topic :: Software Development :: Libraries :: Python Modules
Requires-Dist: django (>=1.7,<1.9)
Requires-Dist: micawber (==0.3.2)
Requires-Dist: djangorestframework (==3.0.0)
Requires-Dist: Pillow (==2.6.1)
Requires-Dist: django-ckeditor (==4.4.8)
